<!DOCTYPE MyLife>
<task name="life">
 <task name="Танцы" id="dancing" cost="0" time="0">
  <task name="hustle" id="hustle" cost="0" time="0"/>
  <task name="kizomba" id="kizomba" cost="12" time="0">
   <task name="индив кизомба" id="kizomba0" cost="2000" time="2"/>
  </task>
  <task name="Зук" id="zouk" cost="0" time="0">
   <task name="повторить видео" id="zouk video" cost="0" time="5"/>
   <link with="kizomba"/>
   <task name="зук вечеринки" id="zouk disco" cost="1600" time="8"/>
   <task name="занятия по зуку" id="zouk class" cost="4000" time="12"/>
   <task name="мастерклассы по зуку" id="zouk masters" cost="9000" time="12"/>
  </task>
  <task name="Бачата" id="bachata" cost="0" time="0">
   <task name="индив bachata" id="bachata0" cost="2000" time="2"/>
   <task name="видео от кати" id="bachata00" cost="0" time="0">
    <task name="виртуально" id="bachata000" cost="0" time="2"/>
    <task name="отработать" id="bachata0000" cost="0" time="1"/>
   </task>
  </task>
  <task name="музыкальность" id="music sence" cost="0" time="4"/>
 </task>
 <task name="Спорт" id="sport" cost="0" time="0"/>
 <task name="Встреча" id="meeting" cost="0" time="0">
  <task name="Маша" id="masha" cost="1000" time="2"/>
 </task>
 <task name="спорт" id="id-000" cost="0" time="0"/>
</task>
